zapish_logger/__init__.py
zapish_logger/logger.py
zapish_logger/py.typed
zapish_logger-1.1.3.dist-info/licenses/LICENSE
zapish_logger-1.1.3.dist-info/METADATA
zapish_logger-1.1.3.dist-info/WHEEL
zapish_logger-1.1.3.dist-info/top_level.txt
zapish_logger-1.1.3.dist-info/RECORD
