Metadata-Version: 2.4
Name: zapish-logger
Version: 1.1.3
Summary: A simple logger that logs in a JSON format inspired by go zap
Author-email: "Benjamin P. Trachtenberg" <e_ben_75-python@yahoo.com>
Maintainer-email: "Benjamin P. Trachtenberg" <e_ben_75-python@yahoo.com>
License-Expression: MIT
Project-URL: Documentation, https://zapish-logger.readthedocs.io/en/latest/
Project-URL: Source, https://github.com/btr1975/zapish-logger
Project-URL: Tracker, https://github.com/btr1975/zapish-logger/issues
Keywords: logger,structured,json
Classifier: Development Status :: 5 - Production/Stable
Classifier: Intended Audience :: Developers
Classifier: Natural Language :: English
Classifier: Operating System :: MacOS :: MacOS X
Classifier: Operating System :: POSIX
Classifier: Operating System :: POSIX :: BSD
Classifier: Operating System :: POSIX :: Linux
Classifier: Operating System :: Microsoft :: Windows
Classifier: Programming Language :: Python :: 3
Classifier: Programming Language :: Python :: 3 :: Only
Classifier: Programming Language :: Python :: 3.9
Classifier: Programming Language :: Python :: 3.10
Classifier: Programming Language :: Python :: 3.11
Classifier: Programming Language :: Python :: 3.12
Classifier: Programming Language :: Python :: 3.13
Classifier: Programming Language :: Python :: 3.14
Requires-Python: >=3.9
License-File: LICENSE
Dynamic: license-file
